pyamaxkit/ABI.py
pyamaxkit/__init__.py
pyamaxkit/_pyeoskit.cpython-39-darwin.so
pyamaxkit/block_log.py
pyamaxkit/chainapi.py
pyamaxkit/chainapi_async.py
pyamaxkit/chainapi_sync.py
pyamaxkit/chaincache.py
pyamaxkit/chainnative.py
pyamaxkit/common.py
pyamaxkit/compiler.py
pyamaxkit/config.py
pyamaxkit/crypto.py
pyamaxkit/defaultabi.py
pyamaxkit/eosBase.py
pyamaxkit/exceptions.py
pyamaxkit/google_docstring.py
pyamaxkit/http_client.py
pyamaxkit/ledger.py
pyamaxkit/log.py
pyamaxkit/rpc_interface.py
pyamaxkit/test_helper.py
pyamaxkit/testnet.py
pyamaxkit/transaction.py
pyamaxkit/utils.py
pyamaxkit/wallet.py
pyamaxkit/wasmcompiler.py
pyamaxkit/contracts/eosio.bios/eosio.bios.abi
pyamaxkit/contracts/eosio.bios/eosio.bios.wasm
pyamaxkit/contracts/eosio.msig/eosio.msig.abi
pyamaxkit/contracts/eosio.msig/eosio.msig.wasm
pyamaxkit/contracts/eosio.system/eosio.system.abi
pyamaxkit/contracts/eosio.system/eosio.system.wasm
pyamaxkit/contracts/eosio.token/eosio.token.abi
pyamaxkit/contracts/eosio.token/eosio.token.wasm
pyamaxkit/contracts/eosio.wrap/eosio.wrap.abi
pyamaxkit/contracts/eosio.wrap/eosio.wrap.wasm
pyamaxkit/contracts/micropython/micropython.abi
pyamaxkit/contracts/micropython/micropython.wasm
pyamaxkit/contracts/micropython/micropython_eosio.wasm
pyamaxkit/data/eosio.system_eosio.abi
pyamaxkit/data/eosio.system_uuos.abi
pyamaxkit/data/eosio.token.abi
pyamaxkit-1.0.8.data/data/.gitignore
pyamaxkit-1.0.8.data/data/.gitmodules
pyamaxkit-1.0.8.data/data/.readthedocs.yml
pyamaxkit-1.0.8.data/data/CMakeLists.txt
pyamaxkit-1.0.8.data/data/LICENSE
pyamaxkit-1.0.8.data/data/README.md
pyamaxkit-1.0.8.data/data/build.sh
pyamaxkit-1.0.8.data/data/cython
pyamaxkit-1.0.8.data/data/gen_docs.sh
pyamaxkit-1.0.8.data/data/install.sh
pyamaxkit-1.0.8.data/data/mkdocs.yml
pyamaxkit-1.0.8.data/data/pyproject.toml
pyamaxkit-1.0.8.data/data/release.txt
pyamaxkit-1.0.8.data/data/requirements-dev.txt
pyamaxkit-1.0.8.data/data/requirements.txt
pyamaxkit-1.0.8.data/data/setup.cfg
pyamaxkit-1.0.8.dist-info/LICENSE
pyamaxkit-1.0.8.dist-info/METADATA
pyamaxkit-1.0.8.dist-info/WHEEL
pyamaxkit-1.0.8.dist-info/top_level.txt
pyamaxkit-1.0.8.dist-info/RECORD
