Metadata-Version: 2.1
Name: pyamaxkit
Version: 1.0.8
Summary: Python Toolkit for AMAX
Home-page: https://github.com/AMAX-DAO-DEV/pyamaxkit
Author: learnforpractice
License: MIT
License-File: LICENSE
Requires-Dist: requests-unixsocket (>=0.2.0)
Requires-Dist: httpx (>=0.19.0)
Requires-Dist: base58 (>=2.1.1)
Requires-Dist: asn1 (>=2.4.2)
Requires-Dist: ledgerblue (>=0.1.41)
